[
    {
        "input_combination": [
            {
                "type": 1,
                "code": 104,
                "origin_hash": "dc43286e4f1fbeefa438d35b80fed28a"
            }
        ],
        "target_uinput": "keyboard",
        "output_symbol": "KEY_HOME",
        "mapping_type": "key_macro"
    },
    {
        "input_combination": [
            {
                "type": 1,
                "code": 109,
                "origin_hash": "dc43286e4f1fbeefa438d35b80fed28a"
            }
        ],
        "target_uinput": "keyboard",
        "output_symbol": "KEY_END",
        "mapping_type": "key_macro"
    },
    {
        "input_combination": [
            {
                "type": 1,
                "code": 102,
                "origin_hash": "dc43286e4f1fbeefa438d35b80fed28a"
            }
        ],
        "target_uinput": "keyboard",
        "output_symbol": "KEY_PAGEUP",
        "mapping_type": "key_macro"
    },
    {
        "input_combination": [
            {
                "type": 1,
                "code": 107,
                "origin_hash": "dc43286e4f1fbeefa438d35b80fed28a"
            }
        ],
        "target_uinput": "keyboard",
        "output_symbol": "KEY_PAGEDOWN",
        "mapping_type": "key_macro"
    }
]
